<?xml version="1.0"?>
<!DOCTYPE FastPathXML SYSTEM "types.dtd">
<FastPathXML>
  <data-types version="1.0">
    <type decode="xLibDecode_int" encode="xLibEncode_int" name="int" validation="validate_int" value="XLIB_DTYPE_int"/>
    <type decode="xLibDecode_uint" encode="xLibEncode_uint" name="uint" validation="validate_uint" value="XLIB_DTYPE_uint"/>
    <type decode="xLibDecode_uint64" encode="xLibEncode_uint64" name="uint64" validation="validate_uint" value="XLIB_DTYPE_uint64"/>
    <type decode="xLibDecode_string" encode="xLibEncode_string" name="string" validation="validate_string" value="XLIB_DTYPE_string"/>
    <type decode="xLibDecode_ipv4" encode="xLibEncode_ipv4" name="ipv4" validation="validate_ipv4" value="XLIB_DTYPE_ipv4"/>
    <type decode="xLibDecode_ipv6" encode="xLibEncode_ipv6" name="ipv6" validation="validate_ipv6" value="XLIB_DTYPE_ipv6"/>
    <type decode="xLibDecode_mac" encode="xLibEncode_mac" name="mac" validation="validate_mac" value="XLIB_DTYPE_mac"/>
<!--
    <type decode="xLibDecode_intRange_t" encode="xLibEncode_intRange_t" name="intRange_t" validation="validate_int_range" value="XLIB_DTYPE_intRange_t"/>
    <type decode="xLibDecode_uspRange_t" encode="xLibEncode_uspRange_t" name="uspRange_t" validation="validate_usp_range" value="XLIB_DTYPE_uspRange_t"/>
-->
  </data-types>
</FastPathXML>
